[
  {
    "name": "SockyWocky",
    "color": "#c369ff",
    "textures": [
      { "file": "canvas_default.png", "v": 1 },
      { "file": "canvas_red.png", "v": 1 },
      { "file": "canvas_brown.png", "v": 1 },
      { "file": "canvas_orange.png", "v": 1 },
      { "file": "canvas_yellow.png", "v": 1 },
      { "file": "canvas_green.png", "v": 1 },
      { "file": "canvas_lime.png", "v": 1 },
      { "file": "canvas_cyan.png", "v": 1 },
      { "file": "canvas_light_blue.png", "v": 1 },
      { "file": "canvas_blue.png", "v": 1 },
      { "file": "canvas_purple.png", "v": 1 },
      { "file": "canvas_magenta.png", "v": 1 },
      { "file": "canvas_pink.png", "v": 1 },
      { "file": "canvas_white.png", "v": 1 },
      { "file": "canvas_light_gray.png", "v": 1 },
      { "file": "canvas_gray.png", "v": 1 },
      { "file": "canvas_black.png", "v": 1 }
    ]
  },
  {
    "name": "Arthur",
    "color": "#57bcff",
    "textures": [
      { "file": "nixieboard.png", "v": 2 }
    ]
  },
  {
    "name": "The Tophatted Dolphin",
    "color": "#30FF4B",
    "textures": [
      { "file": "stickynote.png", "v": 1 }
    ]
  },
  {
    "name": "lanlan3292",
    "color": "#9cb7e7",
    "textures": [
      { "file": "vanilla.png", "v": 1 },
      { "file": "vanilla2.png", "v": 1 },
      { "file": "ae2.png", "v": 1 },
      { "file": "ae2_dark.png", "v": 1 },
      { "file": "create.png", "v": 1 },
      { "file": "blueprint.png", "v": 1 }
    ]
  }
]
